libname/__init__.py
libname/praxpypy.py
praxpypy-0.0.1.dist-info/METADATA
praxpypy-0.0.1.dist-info/WHEEL
praxpypy-0.0.1.dist-info/top_level.txt
praxpypy-0.0.1.dist-info/RECORD
